{
  "name": "Config",
  "groups": [
    {
      "objType": "CGroup",
      "elementName": "Group",
      "instrument": "Piano",
      "chained": false,
      "thickenFlag": false,
      "tempoMs": 500,
      "seqMode": "None",
      "arpFlag": false,
      "arpNPB": 4,
      "arpSequence": "1234",
      "tremRate": 1,
      "envelope": "Fast",
      "elements": [],
      "masterLevel": 100,
      "distortionLevel": 0,
      "chorusLevel": 0,
      "phaserLevel": 0,
      "tremoloLevel": 0,
      "dryLevel": 100,
      "reverbLevel": 0,
      "delayLevel": 0
    },
    {
      "objType": "CGroup",
      "elementName": "Group",
      "instrument": "Piano",
      "chained": false,
      "thickenFlag": false,
      "tempoMs": 500,
      "seqMode": "None",
      "arpFlag": false,
      "arpNPB": 4,
      "arpSequence": "1234",
      "tremRate": 1,
      "envelope": "Fast",
      "elements": [],
      "masterLevel": 100,
      "distortionLevel": 0,
      "chorusLevel": 0,
      "phaserLevel": 0,
      "tremoloLevel": 0,
      "dryLevel": 100,
      "reverbLevel": 0,
      "delayLevel": 0
    },
    {
      "objType": "CGroup",
      "elementName": "Clipboard",
      "instrument": "Piano",
      "chained": false,
      "thickenFlag": false,
      "tempoMs": 500,
      "seqMode": "None",
      "arpFlag": false,
      "arpNPB": 4,
      "arpSequence": "1234",
      "tremRate": 1,
      "envelope": "Fast",
      "elements": [],
      "masterLevel": 100,
      "distortionLevel": 0,
      "chorusLevel": 0,
      "phaserLevel": 0,
      "tremoloLevel": 0,
      "dryLevel": 100,
      "reverbLevel": 0,
      "delayLevel": 0
    }
  ]
}